lyla/__about__.py
lyla/__init__.py
lyla/combine_and_flatten.py
lyla/extract_authors.py
lyla/figure.py
lyla/latex_file_modifier.py
lyla/pythontex_liaison.py
lyla-0.1.0.dist-info/METADATA
lyla-0.1.0.dist-info/WHEEL
lyla-0.1.0.dist-info/RECORD
